PyKomoran/__init__.py
PyKomoran/__version__.py
PyKomoran/core.py
PyKomoran/jvm.py
PyKomoran/type.py
PyKomoran/libs/.DS_Store
PyKomoran/libs/KOMORAN-3.3.9.jar
PyKomoran/libs/KOMORANEntryPoint-0.1.6.jar
PyKomoran/libs/py4j-0.10.9.2.jar
PyKomoran/libs/py4j0.10.8.1.jar
PyKomoran/tests/__init__.py
PyKomoran/tests/test__jvm.py
PyKomoran/tests/test_core.py
PyKomoran/tests/test_type.py
PyKomoran/tests/test_data/dic.user
PyKomoran/tests/test_data/fwd.user
PyKomoran-0.1.6.post1.dist-info/LICENSE
PyKomoran-0.1.6.post1.dist-info/METADATA
PyKomoran-0.1.6.post1.dist-info/WHEEL
PyKomoran-0.1.6.post1.dist-info/top_level.txt
PyKomoran-0.1.6.post1.dist-info/RECORD
