Metadata-Version: 2.1
Name: PyKomoran
Version: 0.1.6.post1
Summary: PyKomoran is Python wrapper for KOMORAN, KOrean MORphical ANalyzer.
Home-page: https://pydocs.komoran.kr
Author: Junghwan Park, Junsoo Shin, Geunho Lee
Author-email: shineware.contact.form@gmail.com
Maintainer: Junghwan Park, Junsoo Shin, Geunho Lee
Maintainer-email: shineware.contact.form@gmail.com
License: Apache 2.0
Download-URL: https://github.com/shineware/PyKOMORAN/releases/download/0.1.6.post1/PyKomoran-0.1.6.post1.tar.gz
Keywords: KOMORAN,KOrean MORphical ANalyzer,MORphical Analyzer,Text Analyzer,Tokenizer,PoS Tagger,Korean,Linguistic,NLP,Natural Language Processing
Platform: UNKNOWN
Classifier: Development Status :: 4 - Beta
Classifier: Environment :: Console
Classifier: Intended Audience :: Developers
Classifier: Intended Audience :: Education
Classifier: Intended Audience :: Information Technology
Classifier: Intended Audience :: Science/Research
Classifier: License :: OSI Approved :: Apache Software License
Classifier: Natural Language :: Korean
Classifier: Programming Language :: Java
Classifier: Programming Language :: Python :: 3 :: Only
Classifier: Programming Language :: Python :: 3.4
Classifier: Programming Language :: Python :: 3.5
Classifier: Programming Language :: Python :: 3.6
Classifier: Programming Language :: Python :: 3.7
Classifier: Topic :: Scientific/Engineering :: Information Analysis
Classifier: Topic :: Software Development :: Libraries :: Java Libraries
Classifier: Topic :: Text Processing :: Linguistic
Provides-Extra: test
